cgkmc/__init__.py
cgkmc/containers.py
cgkmc/simulations.py
cgkmc/utils.py
cgkmc-0.1.1.dist-info/METADATA
cgkmc-0.1.1.dist-info/WHEEL
cgkmc-0.1.1.dist-info/entry_points.txt
cgkmc-0.1.1.dist-info/licenses/LICENSE
cgkmc-0.1.1.dist-info/RECORD
