Metadata-Version: 2.4
Name: cgkmc
Version: 0.1.1
Summary: Crystal Growth Kinetic Monte Carlo
Project-URL: Homepage, https://github.com/jwjeffr/cgkmc
License-Expression: MIT
License-File: LICENSE
Keywords: crystal,graph,growth,kmc,morphology,nanocrystal,surface
Classifier: Programming Language :: Python :: 3.9
Classifier: Programming Language :: Python :: 3.10
Classifier: Programming Language :: Python :: 3.11
Classifier: Programming Language :: Python :: 3.12
Requires-Python: >=3.9
Requires-Dist: numpy~=2.0.2
Requires-Dist: scipy~=1.13.1
Provides-Extra: dev
Requires-Dist: hatchling~=1.27.0; extra == 'dev'
Requires-Dist: mypy~=1.13.0; extra == 'dev'
Requires-Dist: pdoc~=15.0.1; extra == 'dev'
Requires-Dist: pytest~=8.0.2; extra == 'dev'
Requires-Dist: ruff~=0.9.4; extra == 'dev'
